infmidi/__init__.py
infmidi/constants.py
infmidi/exceptions.py
infmidi/utils.py
infmidi/warps.py
infmidi/core/__init__.py
infmidi/core/clip.py
infmidi/core/convert.py
infmidi/core/event.py
infmidi/core/midi.py
infmidi/core/note.py
infmidi/core/track.py
infmidi/devices/TimGM6mb.sf2
infmidi/devices/__init__.py
infmidi/devices/controller.py
infmidi/devices/fluidsynth.py
infmidi/devices/viewer.py
infmidi/effects/__init__.py
infmidi/effects/pitch.py
infmidi/effects/rhythm.py
infmidi/effects/velocity.py
infmidi/generator/__init__.py
infmidi/generator/_chord.py
infmidi/generator/_sheet.py
infmidi-0.1.2.dist-info/LICENSE
infmidi-0.1.2.dist-info/METADATA
infmidi-0.1.2.dist-info/WHEEL
infmidi-0.1.2.dist-info/top_level.txt
infmidi-0.1.2.dist-info/RECORD
