Metadata-Version: 2.1
Name: infmidi
Version: 0.1.2
Summary: Manipulate midi and create music with a simple and high level interface.
Home-page: https://github.com/gongyibei/infmidi
Author: gongyibei
Author-email: gongyibei@gmail.com
License: MIT
Project-URL: Documentation, https://infmidi.readthedocs.io/en/latest/
Project-URL: Code, https://github.com/gongyibei/infmidi
Project-URL: Issue tracker, https://github.com/gongyibei/infmidi/issues
Classifier: Programming Language :: Python :: 3
Classifier: License :: OSI Approved :: MIT License
Classifier: Operating System :: OS Independent
Classifier: Topic :: Multimedia :: Sound/Audio :: MIDI
License-File: LICENSE
Requires-Dist: mido (>=1.1.16)
Requires-Dist: sortedcontainers
Provides-Extra: all
Requires-Dist: matplotlib (>=1.5) ; extra == 'all'
Requires-Dist: numpy (>=1.12.0) ; extra == 'all'
Requires-Dist: python-rtmidi (>=1.1.0) ; extra == 'all'
Provides-Extra: devices
Requires-Dist: python-rtmidi (>=1.1.0) ; extra == 'devices'
Provides-Extra: plot
Requires-Dist: numpy (>=1.12.0) ; extra == 'plot'
Requires-Dist: matplotlib (>=1.5) ; extra == 'plot'
